comoresolve/__init__.py
comoresolve/__main__.py
comoresolve-0.1.0.dist-info/entry_points.txt
comoresolve-0.1.0.dist-info/LICENSE
comoresolve-0.1.0.dist-info/WHEEL
comoresolve-0.1.0.dist-info/METADATA
comoresolve-0.1.0.dist-info/RECORD
